bcanalyzer/app.py
bcanalyzer/common/const.py
bcanalyzer/common/files.py
bcanalyzer/common/io.py
bcanalyzer/common/settings.py
bcanalyzer/common/singleton.py
bcanalyzer/gui/controllers/basic_controller.py
bcanalyzer/gui/controllers/main_controller.py
bcanalyzer/gui/models/processing_list_model.py
bcanalyzer/gui/models/processing_preview_model.py
bcanalyzer/gui/resources/logo.ico
bcanalyzer/gui/views/main_window.py
bcanalyzer/gui/widgets/about_widget.py
bcanalyzer/gui/widgets/extended_slider_widget.py
bcanalyzer/gui/widgets/processing_list_widget.py
bcanalyzer/gui/widgets/processing_preview_widget.py
bcanalyzer/image_processing/image_processor.py
bcanalyzer/image_processing/utils.py
bio_cntrs_analyzer-0.2.1.dist-info/LICENSE
bio_cntrs_analyzer-0.2.1.dist-info/METADATA
bio_cntrs_analyzer-0.2.1.dist-info/WHEEL
bio_cntrs_analyzer-0.2.1.dist-info/entry_points.txt
bio_cntrs_analyzer-0.2.1.dist-info/RECORD
