Metadata-Version: 2.1
Name: bio-cntrs-analyzer
Version: 0.2.1
Summary: The semi-automatic segmentation and quantification of patchy areas in various biomedical images based on the assessment of their local edge densities.
Home-page: https://gitlab.com/digiratory/biomedimaging/bcanalyzer
License: GPL-3.0-or-later
Author: Aleksandr Sinitca
Author-email: amsinitca@etu.ru
Requires-Python: >=3.7,<4.0
Classifier: License :: OSI Approved :: GNU General Public License v3 or later (GPLv3+)
Classifier: Programming Language :: Python :: 3
Classifier: Programming Language :: Python :: 3.7
Classifier: Programming Language :: Python :: 3.8
Classifier: Programming Language :: Python :: 3.9
Classifier: Programming Language :: Python :: 3.10
Classifier: Programming Language :: Python :: 3.11
Requires-Dist: PyQt5
Requires-Dist: appdirs
Requires-Dist: filetype
Requires-Dist: numpy (>=1.19.0,<2.0.0)
Requires-Dist: opencv-python (>=4.5,<5.0)
Requires-Dist: opencv-python-headless
Requires-Dist: pandas
Requires-Dist: scipy
Requires-Dist: sdd-segmentation
Project-URL: Repository, https://gitlab.com/digiratory/biomedimaging/bcanalyzer
